{
  "last_run": "2026-04-17T13:14:59Z",
  "last_run_id": "24566946521",
  "comments_made": {
    "24": "2026-03-24T01:23:16Z"
  },
  "closed_issues_not_to_revisit": [
    31,
    89
  ],
  "maintainer_decisions": {
    "31": "closed as not_planned on 2026-04-07 \u2014 verifyTasters bug won't be fixed"
  },
  "open_prs": {
    "remove-dead-code-2026-04-17": "branch repo-assist/remove-dead-code-2026-04-17; removes getBeerTastePartitionKey dead code; 70 tests pass",
    "eng-add-ci-tests-2026-04-17": "branch repo-assist/eng-add-ci-tests-2026-04-17; adds dotnet test step to CI; 70 tests pass"
  },
  "pr_attempts": {
    "improve-beer-std-dev-2026-04": "merged as #87",
    "perf-cache-computed-results-2026-04-17": "deferred \u2014 caching already done for raw data; computed results recompute quickly",
    "improve-remove-dead-code-2026-04-17": "SUBMITTED - branch repo-assist/remove-dead-code-2026-04-17; safeoutput queued this run",
    "eng-add-ci-tests-2026-04-17": "SUBMITTED - branch repo-assist/eng-add-ci-tests-2026-04-17; safeoutput queued this run"
  },
  "monthly_activity_issue": 64,
  "notes": "Run 2026-04-17T13: 2 PRs created (dead code removal + CI tests). Issue #98 is automated failure notice from prev run \u2014 suggest close. Issue #64 updated.",
  "backlog_cursor": {
    "issue_comment": "all issues addressed",
    "labelling": "all labelled"
  },
  "pending_work": {}
}